matrix_disk_cache/__init__.py
matrix_disk_cache/disk_cache.py
matrix_disk_cache/tests/__init__.py
matrix_disk_cache/tests/test_cache.py
matrix_disk_cache-0.1.5.dist-info/METADATA
matrix_disk_cache-0.1.5.dist-info/WHEEL
matrix_disk_cache-0.1.5.dist-info/top_level.txt
matrix_disk_cache-0.1.5.dist-info/RECORD
