Metadata-Version: 2.1
Name: matrix_disk_cache
Version: 0.1.5
Summary: A Python library for disk-based function caching
Home-page: https://github.com/modyf01/Disk-Cache
Author: Krzysztof Ostrowski
Author-email: krzysztofostrowski2001@gmail.com
License: MIT
Classifier: Programming Language :: Python :: 3
Classifier: License :: OSI Approved :: MIT License
Classifier: Operating System :: OS Independent
Requires-Python: >=3.6
Requires-Dist: numpy
Requires-Dist: pandas
